{
  "$schema": "https://turbo.build/schema.json",
  "ui": "tui",
  "tasks": {
    "build": {
      "dependsOn": ["^build"],
      "inputs": ["$TURBO_DEFAULT$", ".env*"],
      "outputs": [".next/**", "!.next/cache/**", "dist/**"]
    },
    "lint": {
      "dependsOn": ["^lint"]
    },
    "transit": {
      "dependsOn": ["^transit"]
    },
    "check-types": {
      "dependsOn": ["transit"]
    },
    "dev": {
      "cache": false,
      "persistent": true,
      "inputs": ["$TURBO_DEFAULT$", ".env*"]
    }
  }
}
